{"nodes": [{"id": "requests_api_request_metrics", "label": "API Request Metrics", "file_type": "document", "source_file": "logs/requests.json", "source_location": null, "source_url": null, "captured_at": null, "author": null, "contributor": null}], "edges": [{"source": "requests_api_request_metrics", "target": "run2_summary_second_run_evaluation_vector", "relation": "shares_data_with", "confidence": "INFERRED", "confidence_score": 0.95, "source_file": "logs/requests.json", "source_location": null, "weight": 1.0}], "hyperedges": []}